{
    "uuids": {
        "phone_id": "878919d1-0313-49f9-9cac-dd006610fb01",
        "uuid": "b97d1e88-4a59-45cd-912f-80fd11f30199",
        "client_session_id": "0cffdbbc-e26d-44b7-b77c-adf7784be714",
        "advertising_id": "0bf15953-9f42-4f61-b709-6ccc2f3f2285",
        "android_device_id": "android-256e72a3a4996877",
        "request_id": "43491756-a48b-42e7-aec9-6b227761a975",
        "tray_session_id": "31ec8e02-3005-4e18-8fc0-a1311af1d2b1"
    },
    "mid": "abzcMAABAAGK4YpigGkhmKUuQfNp",
    "ig_u_rur": null,
    "ig_www_claim": null,
    "authorization_data": {
        "ds_user_id": "78113835616",
        "sessionid": "78113835616%3AvvbCwTHm3s9W9R%3A15%3AAYhugktCGvSDwRbr2c6inujVLLU8hqXGbkQ4p5hlOg"
    },
    "cookies": {},
    "last_login": 1773984829.0240438,
    "device_settings": {
        "app_version": "269.0.0.18.75",
        "android_version": 26,
        "android_release": "8.0.0",
        "dpi": "480dpi",
        "resolution": "1080x1920",
        "manufacturer": "OnePlus",
        "device": "devitron",
        "model": "6T Dev",
        "cpu": "qcom",
        "version_code": "314665256"
    },
    "user_agent": "Instagram 312.0.0.22.114 Android",
    "country": "US",
    "country_code": 1,
    "locale": "en_US",
    "timezone_offset": -14400
}